prismedia/__init__.py
prismedia/__main__.py
prismedia/config/peertube_secret.sample
prismedia/config/youtube_secret.json.sample
prismedia/genconfig.py
prismedia/pt_upload.py
prismedia/samples/cli_nfo.txt
prismedia/samples/full_nfo_examples.txt
prismedia/samples/nfo.txt
prismedia/samples/samples.txt
prismedia/samples/yourvideo.txt
prismedia/upload.py
prismedia/utils.py
prismedia/yt_upload.py
prismedia-0.13.0.dist-info/LICENSE
prismedia-0.13.0.dist-info/METADATA
prismedia-0.13.0.dist-info/WHEEL
prismedia-0.13.0.dist-info/entry_points.txt
prismedia-0.13.0.dist-info/RECORD
