Metadata-Version: 2.3
Name: prismedia
Version: 0.13.0
Summary: scripting your way to upload videos on peertube and youtube
License: AGPL-3.0-only
Keywords: peertube,youtube,prismedia
Author: LecygneNoir
Author-email: git@lecygnenoir.info
Requires-Python: >=3.9
Classifier: License :: OSI Approved :: GNU Affero General Public License v3
Classifier: Programming Language :: Python :: 3
Classifier: Programming Language :: Python :: 3.9
Classifier: Programming Language :: Python :: 3.10
Classifier: Programming Language :: Python :: 3.11
Classifier: Programming Language :: Python :: 3.12
Classifier: Programming Language :: Python :: 3.13
Requires-Dist: Unidecode (>=1.0.23)
Requires-Dist: clint (>=0.5.1)
Requires-Dist: configparser (>=3.7.1)
Requires-Dist: docopt (>=0.6.2)
Requires-Dist: future (>=0.17.1)
Requires-Dist: google-api-python-client (>=1.7.6)
Requires-Dist: google-auth (>=1.6.1)
Requires-Dist: google-auth-httplib2 (>=0.0.3)
Requires-Dist: google-auth-oauthlib (>=0.2.0)
Requires-Dist: httplib2 (>=0.12.1)
Requires-Dist: oauthlib (==2.1.0)
Requires-Dist: pytz (==2022.1)
Requires-Dist: requests (>=2.18.4)
Requires-Dist: requests-oauthlib (==1.1.0)
Requires-Dist: requests-toolbelt (>=0.9.1)
Requires-Dist: schema (>=0.7.1)
Requires-Dist: tzlocal (>=1.5.1)
Requires-Dist: uritemplate (>=3.0.0)
Requires-Dist: urllib3 (>=1.22)
Project-URL: Homepage, https://git.lecygnenoir.info/LecygneNoir/prismedia
Project-URL: Repository, https://git.lecygnenoir.info/LecygneNoir/prismedia
